README.md
setup.cfg
setup.py
src/GetFolderFiles/__init__.py
src/GetFolderFiles.egg-info/PKG-INFO
src/GetFolderFiles.egg-info/SOURCES.txt
src/GetFolderFiles.egg-info/dependency_links.txt
src/GetFolderFiles.egg-info/requires.txt
src/GetFolderFiles.egg-info/top_level.txt