Metadata-Version: 1.0
Name: GetFolderFiles
Version: 0.5.0
Summary: Python wrapper library for the get file list in a folder
Home-page: UNKNOWN
Author: Greg He
Author-email: greg.he@expeditors.com
License: MIT
Platform: UNKNOWN
